haidra_core/__init__.py
haidra_core/_version.py
haidra_core/py.typed
haidra_core/service_base.py
haidra_core/ai_horde/__init__.py
haidra_core/ai_horde/meta.py
haidra_core/ai_horde/settings.py
haidra_core/meta/__init__.py
haidra_core-0.0.5.dist-info/licenses/LICENSE
haidra_core-0.0.5.dist-info/METADATA
haidra_core-0.0.5.dist-info/WHEEL
haidra_core-0.0.5.dist-info/top_level.txt
haidra_core-0.0.5.dist-info/RECORD
