Metadata-Version: 2.4
Name: haidra_core
Version: 0.0.5
Summary: Core abstractions for the haidra-org ecosystem.
Author-email: tazlin <tazlin.on.github@gmail.com>
License: GNU AFFERO GENERAL PUBLIC LICENSE
Classifier: Programming Language :: Python :: 3
Classifier: Operating System :: OS Independent
Classifier: License :: OSI Approved :: GNU Affero General Public License v3
Classifier: Development Status :: 4 - Beta
Requires-Python: >=3.10
License-File: LICENSE
Requires-Dist: pydantic>=2.11.7
Requires-Dist: pydantic-settings>=2.10.1
Dynamic: license-file
